etl_tools/__init__.py
etl_tools/extract_tools.py
etl_tools/file_tools.py
etl_tools/load_tools.py
etl_tools/transform_tools.py
example_package/__init__.py
example_package/example.py
DACPYLib-0.0.9.dist-info/METADATA
DACPYLib-0.0.9.dist-info/WHEEL
DACPYLib-0.0.9.dist-info/top_level.txt
DACPYLib-0.0.9.dist-info/RECORD
