Metadata-Version: 2.1
Name: DACPYLib
Version: 0.0.9
Summary: DAC Toolset package
Home-page: https://github.com/pypa/DACPYLib
Author: Kevin Long
Author-email: kevin.long@pennhealth.upenn.edu
License: UNKNOWN
Platform: UNKNOWN
Classifier: Programming Language :: Python :: 3
Classifier: License :: OSI Approved :: MIT License
Classifier: Operating System :: OS Independent
Requires-Python: >=3.6
